{
  "project_info": {
    "project_number": "546436072435",
    "project_id": "pole-searcher",
    "storage_bucket": "pole-searcher.appspot.com"
  },
  "client": [
    {
      "client_info": {
        "mobilesdk_app_id": "1:546436072435:android:7ee0b38cf9ddb4f53f8886",
        "android_client_info": {
          "package_name": "jp.co.genetec.polesearcherapp"
        }
      },
      "oauth_client": [
        {
          "client_id": "546436072435-vfodvkjokv2510oiv5kvvdbcvbm6ci4u.apps.googleusercontent.com",
          "client_type": 3
        }
      ],
      "api_key": [
        {
          "current_key": "AIzaSyA41Mr728miYGF8dNxZizzlnwpMvvCM7x0"
        }
      ],
      "services": {
        "appinvite_service": {
          "other_platform_oauth_client": [
            {
              "client_id": "546436072435-vfodvkjokv2510oiv5kvvdbcvbm6ci4u.apps.googleusercontent.com",
              "client_type": 3
            },
            {
              "client_id": "546436072435-r5ltv36qpu1nkjuugbtmfj8umtf4966n.apps.googleusercontent.com",
              "client_type": 2,
              "ios_info": {
                "bundle_id": "jp.co.genetec.randd.polesearcherapp"
              }
            }
          ]
        }
      }
    }
  ],
  "configuration_version": "1"
}